tenso/__init__.py
tenso/async_core.py
tenso/config.py
tenso/core.py
tenso/fastapi.py
tenso/gpu.py
tenso/grpc/__init__.py
tenso/grpc/benchmark_msg.proto
tenso/grpc/tenso_msg.proto
tenso/utils.py
tenso-0.12.1.dist-info/WHEEL
tenso-0.12.1.dist-info/METADATA
tenso-0.12.1.dist-info/RECORD
