Metadata-Version: 2.3
Name: tenso
Version: 0.12.1
Summary: High-performance zero-copy tensor protocol
Requires-Dist: lz4>=4.4.5
Requires-Dist: numpy
Requires-Dist: xxhash>=3.6.0
Requires-Dist: fastapi ; extra == 'api'
Requires-Dist: uvicorn ; extra == 'api'
Requires-Dist: httpx>=0.28.1 ; extra == 'dev'
Requires-Dist: myst-parser>=4.0.1 ; extra == 'dev'
Requires-Dist: furo>=2025.9.25 ; extra == 'dev'
Requires-Dist: pytest-asyncio>=1.3.0 ; extra == 'dev'
Requires-Dist: psutil>=7.1.3 ; extra == 'dev'
Requires-Dist: msgpack>=1.1.2 ; extra == 'dev'
Requires-Dist: pyarrow>=22.0.0 ; extra == 'dev'
Requires-Dist: safetensors>=0.7.0 ; extra == 'dev'
Requires-Dist: build>=1.3.0 ; extra == 'dev'
Requires-Dist: pytest>=9.0.1 ; extra == 'dev'
Requires-Dist: twine>=6.2.0 ; extra == 'dev'
Requires-Dist: sphinx>=8.1.3 ; extra == 'dev'
Requires-Dist: sphinx-autodoc-typehints>=3.0.1 ; extra == 'dev'
Requires-Dist: sphinx-rtd-theme>=3.0.0 ; extra == 'dev'
Requires-Dist: ml-dtypes>=0.4.0 ; extra == 'dev'
Requires-Dist: cupy-cuda12x ; sys_platform != 'darwin' and extra == 'gpu'
Requires-Dist: torch ; extra == 'gpu'
Requires-Dist: jax[cuda] ; sys_platform != 'darwin' and extra == 'gpu'
Requires-Dist: jax ; sys_platform == 'darwin' and extra == 'gpu'
Requires-Dist: grpcio>=1.76.0 ; extra == 'grpc'
Requires-Dist: grpcio-tools>=1.76.0 ; extra == 'grpc'
Requires-Python: >=3.10
Provides-Extra: api
Provides-Extra: dev
Provides-Extra: gpu
Provides-Extra: grpc
